phenosentry/__init__.py
phenosentry/auditor/__init__.py
phenosentry/auditor/_api.py
phenosentry/auditor/cohort.py
phenosentry/auditor/phenopacket.py
phenosentry/io/__init__.py
phenosentry/io/_reader.py
phenosentry-0.3.1.dist-info/METADATA
phenosentry-0.3.1.dist-info/WHEEL
phenosentry-0.3.1.dist-info/licenses/LICENSE
phenosentry-0.3.1.dist-info/RECORD
