Metadata-Version: 2.4
Name: phenosentry
Version: 0.3.1
Summary: A tool and library for quality control and validation of GA4GH Phenopackets.
License-File: LICENSE
Author: Michael Gargano
Author-email: Michael.Gargano@jax.org
Requires-Python: >=3.10
Classifier: Programming Language :: Python :: 3
Classifier: Programming Language :: Python :: 3.10
Classifier: Programming Language :: Python :: 3.11
Classifier: Programming Language :: Python :: 3.12
Classifier: Programming Language :: Python :: 3.13
Classifier: Programming Language :: Python :: 3.14
Requires-Dist: hpo-toolkit (>=0.5.5,<0.6.0)
Requires-Dist: phenopackets (>=2.0.2.post4,<3.0.0)
Requires-Dist: stairval (>=0.2.3,<0.3.0)
